antifungal/__init__.py
antifungal/analyze.py
antifungal/design.py
antifungal/predict.py
antifungal/ChemoinfoPy/FeatureSelection.py
antifungal/ChemoinfoPy/PeptideMass.py
antifungal/ChemoinfoPy/ProteinTools.py
antifungal/ChemoinfoPy/SampleSplit.py
antifungal/ChemoinfoPy/__init__.py
antifungal/models/cmodel.pkl
antifungal/models/rmodel_C_a.pkl
antifungal/models/rmodel_C_k.pkl
antifungal/models/rmodel_C_n.pkl
antifungal/models/rmodel_C_p.pkl
antifungal/propy/AAComposition.py
antifungal/propy/AAIndex.py
antifungal/propy/Autocorrelation.py
antifungal/propy/CTD.py
antifungal/propy/GetProteinFromUniprot.py
antifungal/propy/GetSubSeq.py
antifungal/propy/ProCheck.py
antifungal/propy/PseudoAAC.py
antifungal/propy/PyPro.py
antifungal/propy/QuasiSequenceOrder.py
antifungal/propy/__init__.py
antifungal/propy/data/grantham-chemical-distance-matrix.json
antifungal/propy/data/hydrophilicity.json
antifungal/propy/data/hydrophobicity.json
antifungal/propy/data/pI.json
antifungal/propy/data/pK1.json
antifungal/propy/data/pK2.json
antifungal/propy/data/residuemass.json
antifungal/propy/data/schneider-wrede-physicochemical-distance-matrix.json
antifungal-0.1.3.dist-info/METADATA
antifungal-0.1.3.dist-info/WHEEL
antifungal-0.1.3.dist-info/top_level.txt
antifungal-0.1.3.dist-info/RECORD
