Metadata-Version: 2.1
Name: antifungal
Version: 0.1.3
Summary: A python package for activity prediction and rational design of antifungal peitdes.
Home-page: https://github.com/JinZhangLab/antifungal
Author: Jin Zhang
Author-email: jzhang@chemoinfolab.com
Classifier: License :: OSI Approved :: MIT License
Classifier: Programming Language :: Python :: 3.6
Classifier: Programming Language :: Python :: 3.7
Classifier: Programming Language :: Python :: 3.8
Requires-Python: >=3.6, <3.9
Requires-Dist: numpy >=1.13.3
Requires-Dist: pandas >=1.2.4
Requires-Dist: modlamp >=4.3.0
Requires-Dist: scipy <=1.7.0
Requires-Dist: scikit-learn ==0.24.2
Requires-Dist: tqdm
Requires-Dist: matplotlib
